<?xml version="1.0" encoding="UTF-8"?>
<cells>
    <cell>
        <!-- 地址码-向上行走距离-向下行走距离-向左行走距离-向右行走距离  使用默认距离用0 -->
        4-0-0-0-1438
    </cell>
    <cell>
        5-0-0-1438-1438
    </cell>
    <cell>
        14-0-0-0-1438
    </cell>
    <cell>
        15-0-0-1438-1438
    </cell>
    <cell>
        24-0-0-0-1438
    </cell>
    <cell>
        25-0-0-1438-1438
    </cell>
    <cell>
        34-0-0-0-1438
    </cell>
    <cell>
        35-0-0-1438-1438
    </cell>
    <cell>
        44-0-0-0-1438
    </cell>
    <cell>
        45-0-0-1438-1438
    </cell>
    <cell>
        54-0-0-0-1438
    </cell>
    <cell>
        55-0-0-1438-1438
    </cell>
    <cell>
        64-0-0-0-1438
    </cell>
    <cell>
        65-0-0-1438-1438
    </cell>
    <cell>
        74-0-0-0-1438
    </cell>
    <cell>
        75-0-0-1438-1438
    </cell>
</cells>













